google_flow_downloader/__init__.py
google_flow_downloader/cli.py
google_flow_downloader-1.1.0.dist-info/METADATA
google_flow_downloader-1.1.0.dist-info/WHEEL
google_flow_downloader-1.1.0.dist-info/entry_points.txt
google_flow_downloader-1.1.0.dist-info/top_level.txt
google_flow_downloader-1.1.0.dist-info/RECORD
