Metadata-Version: 2.4
Name: google-flow-downloader
Version: 1.1.0
Summary: Batch download images from Google Flow
Author: Google Flow Tools
License: MIT
Project-URL: Homepage, https://github.com/neosun100/google-flow-downloader
Keywords: google-flow,image-downloader,ai-tools
Requires-Python: >=3.8
Requires-Dist: requests>=2.31.0
Requires-Dist: rich>=13.0.0
Requires-Dist: click>=8.1.0
